chrc/Chinese_learn.py
chrc/__init__.py
chrc/gif_play.py
chrc/language_coach.py
chrc/playsound.py
chrc-0.3.4.dist-info/METADATA
chrc-0.3.4.dist-info/WHEEL
chrc-0.3.4.dist-info/licenses/LICENSE
chrc-0.3.4.dist-info/RECORD
