Metadata-Version: 2.1
Name: chrc
Version: 0.3.4
Summary: It is a tool to learn Chinese.
Project-URL: Homepage, https://gitee.com/shawnyanwang/chinese-learning-tool
Project-URL: Bug Tracker, https://gitee.com/shawnyanwang/chinese-learning-tool/issues
Author-email: shawn yan wang <shawnyanwang@gmail.com>
License-File: LICENSE
Classifier: License :: OSI Approved :: MIT License
Classifier: Operating System :: OS Independent
Classifier: Programming Language :: Python :: 3
Requires-Python: >=3.7
Requires-Dist: bs4>=0.0.1
Requires-Dist: gtts>=2.2.4
Requires-Dist: jieba>=0.42.1
Requires-Dist: langid>=1.1.6
Requires-Dist: pandas>=1.3.4
Requires-Dist: pillow>=9.0.1
Requires-Dist: playsound>=1.2.2
Requires-Dist: pyaudio>=0.2.12
Requires-Dist: pywin32>=302
Requires-Dist: requests>=2.27.1
Requires-Dist: speechrecognition>=3.8.1
Requires-Dist: thefuzz>=0.19.0
Requires-Dist: tqdm>=4.63.0
Requires-Dist: urllib3>=1.26.8
Requires-Dist: zhon>=1.1.5
